CHANGES.txt
LICENSE.txt
MANIFEST.in
README.rst
requirements_py2.txt
requirements_py3.txt
setup.py
pdfquery/__init__.py
pdfquery/cache.py
pdfquery/pdfquery.py
pdfquery/pdftranslator.py
pdfquery.egg-info/PKG-INFO
pdfquery.egg-info/SOURCES.txt
pdfquery.egg-info/dependency_links.txt
pdfquery.egg-info/pbr.json
pdfquery.egg-info/requires.txt
pdfquery.egg-info/top_level.txt