Metadata-Version: 1.1
Name: pdfquery
Version: 0.4.2
Summary: Concise and friendly PDF scraper using JQuery or XPath selectors.
Home-page: https://github.com/jcushman/pdfquery
Author: Jack Cushman
Author-email: jcushman@gmail.com
License: MIT
Platform: UNKNOWN
Classifier: Development Status :: 4 - Beta
Classifier: Topic :: Text Processing
Classifier: Topic :: Utilities
Classifier: License :: OSI Approved :: MIT License
Classifier: Intended Audience :: Developers
Classifier: Operating System :: OS Independent
Classifier: Programming Language :: Python
Classifier: Programming Language :: Python :: 2
Classifier: Programming Language :: Python :: 2.6
Classifier: Programming Language :: Python :: 2.7
Classifier: Programming Language :: Python :: 3
Classifier: Programming Language :: Python :: 3.3
Classifier: Programming Language :: Python :: 3.4
Classifier: Programming Language :: Python :: 3.5
